Workbook

Sheet GDHM Questions
A1: Indicator 1 -Digital health prioritized at the national level through dedicated bodies / mechanisms for governance Does the country have a separate department / agency / national working group for digital health? | B1: Indicator 2 -Digital Health prioritized at the national level through planning Is digital health included and budgeted for in national health or relevant national strategies and/or plan(s)? Note: The focus of this indicator is on the inclusion of digital health or eHealth in the national health strategy. | C1: Indicator 2a -Health is prioritized in national digital transformation and data governance policies Do national digital transformation and data governance policies and approaches consider and address potential benefits and risks for public health and individual health? | D1: Indicator 3 -Readiness for emerging technologies adoption and governance Is there a national plan specific to emerging technologies (e.g., AI, Wearables, Blockchain, IoT) to support public health goals? | E1: Indicator 4 -Diversity, Equity, and human rights analysis, planning and monitoring included in national digital health strategies and plans Has the country assessed/adapted national digital health strategies from an equity and human rights perspective? | F1: Indicator 4a -Gender considerations accounted for in digital health strategies and digital health governance Does the country include gender considerations in the national digital health strategy or its digital health governance? | G1: Indicator 5 -National eHealth/ Digital Health Strategy or Framework Does the country have an eHealth or digital health strategy or framework and a costed digital health plan? | H1: Indicator 5a -National digital strategy alignment with Universal Health Coverage (UHC) Core Components Is the countryâ€™s national digital health strategy aligned with universal health coverage and/or UHC core components? | I1: Indicator 6 -Public funding for digital health Is public funding (including loans) for digital health sufficient for the digital health strategies, priorities (needs), or costed-plan of the country? | J1: Indicator 6a -Private sector participation and investments in digital health Given the enabling environment, does the private sector participate and invest in digital health activities? | K1: Indicator 7 -Legal Framework for Data Protection (Security/ Cybersecurity) Is there a law on data security (across the full data lifecycle e.g. collection, processing, storage, transmission, use and destruction) that is relevant to digital health? | L1: Indicator 8 -Laws or Regulations for privacy, consent, confidentiality and access to health information (Privacy) Is there a law to protect individual privacy, governing ownership, consent, access and sharing of individually identifiable digital health data ? | M1: Indicator 9 -Protocol for regulating or certifying devices and/or health services- including provisions for AI and algorithms (at higher stages of maturity) Are there protocols, policies, frameworks or accepted processes governing the clinical and patient care use of connected medical devices and health services (e.g. telemedicine, applications), particularly in relation to safety, data integrity and quality of care- including provisions for AI and algorithms (at higher stages of maturity)? | N1: Indicator 9a -Protocol for regulating and certifying AI within health services Are there protocols, policies, frameworks or accepted processes governing the use of AI within health systems, services and applications, particularly in relation to ethics, equity, safety, data integrity and quality of care? | O1: Indicator 10 -Cross-border data security and sharing Are there protocols, policies, frameworks or accepted processes in place to support secure cross-border data exchange and storage in support of public health goals while protecting individual privacy? Note: This includes health-related data coming into a country, going out of a country, and/or being used in a country related to an individual from another country. | P1: Indicator 11 -Digital health integrated in health and related professional pre-service training (prior to deployment) Is digital health part of curriculum for health and health-related support professionals in training, in general? | Q1: Indicator 12 -Digital health integrated in health and related professional in-service training (after to deployment) Specifically, is digital health part of curriculum for health and health-related support professionals in the workforce in general? [Defined as community health workers, nurses, doctors, allied health, health managers/administrators, and technologists] | R1: Indicator 13 -Training of digital health workforce In general, is training in digital health / health informatics / health information systems / biomedical informatics degree programs (in either public or private institutions) producing trained digital health workers? | S1: Indicator 14 -Maturity of public sector digital health professional careers Are there public sector professional titles and career paths in digital health? | T1: Indicator 15 -National digital health architecture and/or health information exchange Is there a national digital health (eHealth) architectural framework and/or health information exchange (HIE) established? | U1: Indicator 16 -Health information standards Are there digital health / health information standards for data exchange, transmission, messaging, security, privacy, and hardware? | V1: Indicator 17 -Network readiness How would you rank Kosovo's network technology as compared to Albania's? (ref: https://networkreadinessindex.org/country/albania/) | W1: Indicator 18 -Planning and support for ongoing digital health infrastructure maintenance Is there an articulated plan for supporting the expansion of digital health infrastructure (including equipment- computers/ tablets/ phones, supplies, software, devices, etc.) provision and maintenance to all public healthcare facilities? | X1: Indicator 19 -Nationally scaled digital health systems Public sector priorities are supported by nationally-scaled digital health systems | Y1: Indicator 20 -Digital identity management of service providers, administrators, and facilities for digital health, including location data for GIS mapping Are health system registries of uniquely identifiable providers, administrators, and public facilities (and private if applicable) available, accessible and current? Is the data geotagged to enable GIS mapping with protocols in place to protect sensitive datasets? | Z1: Indicator 21 -Digital identity management of individuals for health Are secure registries or a master patient index of uniquely identifiable individuals available, fully representative of the population, accessible and current for use for health-related purposes? | AA1: Indicator 21a -Digital identity management of individuals for health Specifically, is there a secure master patient index of uniquely identifiable individuals available, accessible and current for use for health-related purposes? | AB1: Indicator 21b -Digital identity management of individuals for health Specifically, is there a secure birth registry of uniquely identifiable individuals available, accessible and current for use for health-related purposes? | AC1: Indicator 21c -Digital identity management of individuals for health Specifically, is there a secure death registry of uniquely identifiable individuals available, accessible and current for use for health-related purposes? | AD1: Indicator 22 -Secure Patient Feedback Systems Specifically, is there a secure Patient feedback system, available, accessible? | AE1: Indicator 23 -Population health management contribution of digital health Are current country digital health initiatives contributing to public health reporting and decision making?

Sheet Raw Data
B1: Count of Scores | H1: 8 | I1: Enter the number of Google form respondents
A2: GDHM Metric | B2: 1 | C2: 2 | D2: 3 | E2: 4 | F2: 5 | G2: AVG | H2: CHECK | I2: All the CHECK values should be blue
A3: ='GDHM Questions'!A1 -> Indicator 1 -Digital health prioritized at the national level through dedicated bodies / mechanisms for governance Does the country have a separate department / agency / national working group for digital health? | B3: 7 | F3: 1 | G3: =IF(SUM(B3:F3)>0,ROUND((B3+C3*2+D3*3+E3*4+F3*5)/(SUM(B3:F3)),0),0) -> 2 | H3: =SUM(B3:F3) -> 8
A4: ='GDHM Questions'!B1 -> Indicator 2 -Digital Health prioritized at the national level through planning Is digital health included and budgeted for in national health or relevant national strategies and/or plan(s)? Note: The focus of this indicator is on the inclusion of digital health or eHealth in the national health strategy. | B4: 3 | C4: 1 | D4: 2 | E4: 2 | G4: =IF(SUM(B4:F4)>0,ROUND((B4+C4*2+D4*3+E4*4+F4*5)/(SUM(B4:F4)),0),0) -> 2 | H4: =SUM(B4:F4) -> 8
A5: ='GDHM Questions'!C1 -> Indicator 2a -Health is prioritized in national digital transformation and data governance policies Do national digital transformation and data governance policies and approaches consider and address potential benefits and risks for public health and individual health? | C5: 2 | D5: 1 | E5: 4 | F5: 1 | G5: =IF(SUM(B5:F5)>0,ROUND((B5+C5*2+D5*3+E5*4+F5*5)/(SUM(B5:F5)),0),0) -> 4 | H5: =SUM(B5:F5) -> 8
A6: ='GDHM Questions'!D1 -> Indicator 3 -Readiness for emerging technologies adoption and governance Is there a national plan specific to emerging technologies (e.g., AI, Wearables, Blockchain, IoT) to support public health goals? | B6: 5 | C6: 1 | D6: 1 | F6: 1 | G6: =IF(SUM(B6:F6)>0,ROUND((B6+C6*2+D6*3+E6*4+F6*5)/(SUM(B6:F6)),0),0) -> 2 | H6: =SUM(B6:F6) -> 8
A7: ='GDHM Questions'!E1 -> Indicator 4 -Diversity, Equity, and human rights analysis, planning and monitoring included in national digital health strategies and plans Has the country assessed/adapted national digital health strategies from an equity and human rights perspective? | B7: 2 | E7: 3 | F7: 3 | G7: =IF(SUM(B7:F7)>0,ROUND((B7+C7*2+D7*3+E7*4+F7*5)/(SUM(B7:F7)),0),0) -> 4 | H7: =SUM(B7:F7) -> 8
A8: ='GDHM Questions'!F1 -> Indicator 4a -Gender considerations accounted for in digital health strategies and digital health governance Does the country include gender considerations in the national digital health strategy or its digital health governance? | B8: 2 | C8: 1 | D8: 1 | E8: 4 | G8: =IF(SUM(B8:F8)>0,ROUND((B8+C8*2+D8*3+E8*4+F8*5)/(SUM(B8:F8)),0),0) -> 3 | H8: =SUM(B8:F8) -> 8
A9: ='GDHM Questions'!G1 -> Indicator 5 -National eHealth/ Digital Health Strategy or Framework Does the country have an eHealth or digital health strategy or framework and a costed digital health plan? | B9: 1 | D9: 3 | E9: 2 | F9: 2 | G9: =IF(SUM(B9:F9)>0,ROUND((B9+C9*2+D9*3+E9*4+F9*5)/(SUM(B9:F9)),0),0) -> 4 | H9: =SUM(B9:F9) -> 8
A10: ='GDHM Questions'!H1 -> Indicator 5a -National digital strategy alignment with Universal Health Coverage (UHC) Core Components Is the countryâ€™s national digital health strategy aligned with universal health coverage and/or UHC core components? | B10: 2 | D10: 2 | E10: 2 | F10: 2 | G10: =IF(SUM(B10:F10)>0,ROUND((B10+C10*2+D10*3+E10*4+F10*5)/(SUM(B10:F10)),0),0) -> 3 | H10: =SUM(B10:F10) -> 8
A11: ='GDHM Questions'!I1 -> Indicator 6 -Public funding for digital health Is public funding (including loans) for digital health sufficient for the digital health strategies, priorities (needs), or costed-plan of the country? | B11: 1 | C11: 1 | E11: 3 | F11: 3 | G11: =IF(SUM(B11:F11)>0,ROUND((B11+C11*2+D11*3+E11*4+F11*5)/(SUM(B11:F11)),0),0) -> 4 | H11: =SUM(B11:F11) -> 8
A12: ='GDHM Questions'!J1 -> Indicator 6a -Private sector participation and investments in digital health Given the enabling environment, does the private sector participate and invest in digital health activities? | B12: 4 | C12: 3 | D12: 1 | G12: =IF(SUM(B12:F12)>0,ROUND((B12+C12*2+D12*3+E12*4+F12*5)/(SUM(B12:F12)),0),0) -> 2 | H12: =SUM(B12:F12) -> 8
A13: ='GDHM Questions'!K1 -> Indicator 7 -Legal Framework for Data Protection (Security/ Cybersecurity) Is there a law on data security (across the full data lifecycle e.g. collection, processing, storage, transmission, use and destruction) that is relevant to digital health? | B13: 1 | C13: 3 | D13: 1 | F13: 3 | G13: =IF(SUM(B13:F13)>0,ROUND((B13+C13*2+D13*3+E13*4+F13*5)/(SUM(B13:F13)),0),0) -> 3 | H13: =SUM(B13:F13) -> 8
A14: ='GDHM Questions'!L1 -> Indicator 8 -Laws or Regulations for privacy, consent, confidentiality and access to health information (Privacy) Is there a law to protect individual privacy, governing ownership, consent, access and sharing of individually identifiable digital health data ? | C14: 5 | E14: 2 | F14: 1 | G14: =IF(SUM(B14:F14)>0,ROUND((B14+C14*2+D14*3+E14*4+F14*5)/(SUM(B14:F14)),0),0) -> 3 | H14: =SUM(B14:F14) -> 8
A15: ='GDHM Questions'!M1 -> Indicator 9 -Protocol for regulating or certifying devices and/or health services- including provisions for AI and algorithms (at higher stages of maturity) Are there protocols, policies, frameworks or accepted processes governing the clinical and patient care use of connected medical devices and health services (e.g. telemedicine, applications), particularly in relation to safety, data integrity and quality of care- including provisions for AI and algorithms (at higher stages of maturity)? | B15: 3 | C15: 1 | D15: 3 | F15: 1 | G15: =IF(SUM(B15:F15)>0,ROUND((B15+C15*2+D15*3+E15*4+F15*5)/(SUM(B15:F15)),0),0) -> 2 | H15: =SUM(B15:F15) -> 8
A16: ='GDHM Questions'!N1 -> Indicator 9a -Protocol for regulating and certifying AI within health services Are there protocols, policies, frameworks or accepted processes governing the use of AI within health systems, services and applications, particularly in relation to ethics, equity, safety, data integrity and quality of care? | B16: 6 | C16: 1 | E16: 1 | G16: =IF(SUM(B16:F16)>0,ROUND((B16+C16*2+D16*3+E16*4+F16*5)/(SUM(B16:F16)),0),0) -> 2 | H16: =SUM(B16:F16) -> 8
A17: ='GDHM Questions'!O1 -> Indicator 10 -Cross-border data security and sharing Are there protocols, policies, frameworks or accepted processes in place to support secure cross-border data exchange and storage in support of public health goals while protecting individual privacy? Note: This includes health-related data coming into a country, going out of a country, and/or being used in a country related to an individual from another country. | B17: 3 | C17: 2 | D17: 2 | F17: 1 | G17: =IF(SUM(B17:F17)>0,ROUND((B17+C17*2+D17*3+E17*4+F17*5)/(SUM(B17:F17)),0),0) -> 2 | H17: =SUM(B17:F17) -> 8
A18: ='GDHM Questions'!P1 -> Indicator 11 -Digital health integrated in health and related professional pre-service training (prior to deployment) Is digital health part of curriculum for health and health-related support professionals in training, in general? | B18: 6 | C18: 1 | E18: 1 | G18: =IF(SUM(B18:F18)>0,ROUND((B18+C18*2+D18*3+E18*4+F18*5)/(SUM(B18:F18)),0),0) -> 2 | H18: =SUM(B18:F18) -> 8
A19: ='GDHM Questions'!Q1 -> Indicator 12 -Digital health integrated in health and related professional in-service training (after to deployment) Specifically, is digital health part of curriculum for health and health-related support professionals in the workforce in general? [Defined as community health workers, nurses, doctors, allied health, health managers/administrators, and technologists] | B19: 4 | C19: 2 | D19: 1 | E19: 1 | G19: =IF(SUM(B19:F19)>0,ROUND((B19+C19*2+D19*3+E19*4+F19*5)/(SUM(B19:F19)),0),0) -> 2 | H19: =SUM(B19:F19) -> 8
A20: ='GDHM Questions'!R1 -> Indicator 13 -Training of digital health workforce In general, is training in digital health / health informatics / health information systems / biomedical informatics degree programs (in either public or private institutions) producing trained digital health workers? | B20: 4 | C20: 4 | G20: =IF(SUM(B20:F20)>0,ROUND((B20+C20*2+D20*3+E20*4+F20*5)/(SUM(B20:F20)),0),0) -> 2 | H20: =SUM(B20:F20) -> 8
A21: ='GDHM Questions'!S1 -> Indicator 14 -Maturity of public sector digital health professional careers Are there public sector professional titles and career paths in digital health? | B21: 5 | C21: 2 | E21: 1 | G21: =IF(SUM(B21:F21)>0,ROUND((B21+C21*2+D21*3+E21*4+F21*5)/(SUM(B21:F21)),0),0) -> 2 | H21: =SUM(B21:F21) -> 8
A22: ='GDHM Questions'!T1 -> Indicator 15 -National digital health architecture and/or health information exchange Is there a national digital health (eHealth) architectural framework and/or health information exchange (HIE) established? | B22: 4 | C22: 2 | D22: 2 | G22: =IF(SUM(B22:F22)>0,ROUND((B22+C22*2+D22*3+E22*4+F22*5)/(SUM(B22:F22)),0),0) -> 2 | H22: =SUM(B22:F22) -> 8
A23: ='GDHM Questions'!U1 -> Indicator 16 -Health information standards Are there digital health / health information standards for data exchange, transmission, messaging, security, privacy, and hardware? | B23: 3 | C23: 3 | D23: 1 | E23: 1 | G23: =IF(SUM(B23:F23)>0,ROUND((B23+C23*2+D23*3+E23*4+F23*5)/(SUM(B23:F23)),0),0) -> 2 | H23: =SUM(B23:F23) -> 8
A24: Indicator 17 -Network readiness Lookup your country's Network Readiness score. (ref: https://networkreadinessindex.org/countries/#hero) | G24: 45 | H24: Enter country score from https://networkreadinessindex.org
A25: ='GDHM Questions'!W1 -> Indicator 18 -Planning and support for ongoing digital health infrastructure maintenance Is there an articulated plan for supporting the expansion of digital health infrastructure (including equipment- computers/ tablets/ phones, supplies, software, devices, etc.) provision and maintenance to all public healthcare facilities? | B25: 1 | C25: 2 | D25: 1 | E25: 2 | F25: 2 | G25: =IF(SUM(B25:F25)>0,ROUND((B25+C25*2+D25*3+E25*4+F25*5)/(SUM(B25:F25)),0),0) -> 3 | H25: =SUM(B25:F25) -> 8
A26: ='GDHM Questions'!X1 -> Indicator 19 -Nationally scaled digital health systems Public sector priorities are supported by nationally-scaled digital health systems | B26: 1 | C26: 2 | D26: 2 | E26: 2 | F26: 1 | G26: =IF(SUM(B26:F26)>0,ROUND((B26+C26*2+D26*3+E26*4+F26*5)/(SUM(B26:F26)),0),0) -> 3 | H26: =SUM(B26:F26) -> 8
A27: ='GDHM Questions'!Y1 -> Indicator 20 -Digital identity management of service providers, administrators, and facilities for digital health, including location data for GIS mapping Are health system registries of uniquely identifiable providers, administrators, and public facilities (and private if applicable) available, accessible and current? Is the data geotagged to enable GIS mapping with protocols in place to protect sensitive datasets? | B27: 1 | C27: 3 | D27: 4 | G27: =IF(SUM(B27:F27)>0,ROUND((B27+C27*2+D27*3+E27*4+F27*5)/(SUM(B27:F27)),0),0) -> 2 | H27: =SUM(B27:F27) -> 8
A28: ='GDHM Questions'!Z1 -> Indicator 21 -Digital identity management of individuals for health Are secure registries or a master patient index of uniquely identifiable individuals available, fully representative of the population, accessible and current for use for health-related purposes? | B28: 3 | C28: 2 | D28: 1 | E28: 2 | G28: =IF(SUM(B28:F28)>0,ROUND((B28+C28*2+D28*3+E28*4+F28*5)/(SUM(B28:F28)),0),0) -> 2 | H28: =SUM(B28:F28) -> 8
A29: ='GDHM Questions'!AA1 -> Indicator 21a -Digital identity management of individuals for health Specifically, is there a secure master patient index of uniquely identifiable individuals available, accessible and current for use for health-related purposes? | B29: 4 | C29: 1 | D29: 1 | E29: 1 | F29: 1 | G29: =IF(SUM(B29:F29)>0,ROUND((B29+C29*2+D29*3+E29*4+F29*5)/(SUM(B29:F29)),0),0) -> 2 | H29: =SUM(B29:F29) -> 8
A30: ='GDHM Questions'!AB1 -> Indicator 21b -Digital identity management of individuals for health Specifically, is there a secure birth registry of uniquely identifiable individuals available, accessible and current for use for health-related purposes? | B30: 2 | C30: 1 | E30: 1 | F30: 4 | G30: =IF(SUM(B30:F30)>0,ROUND((B30+C30*2+D30*3+E30*4+F30*5)/(SUM(B30:F30)),0),0) -> 4 | H30: =SUM(B30:F30) -> 8
A31: ='GDHM Questions'!AC1 -> Indicator 21c -Digital identity management of individuals for health Specifically, is there a secure death registry of uniquely identifiable individuals available, accessible and current for use for health-related purposes? | B31: 1 | C31: 2 | D31: 1 | E31: 1 | F31: 3 | G31: =IF(SUM(B31:F31)>0,ROUND((B31+C31*2+D31*3+E31*4+F31*5)/(SUM(B31:F31)),0),0) -> 3 | H31: =SUM(B31:F31) -> 8
A32: ='GDHM Questions'!AD1 -> Indicator 22 -Secure Patient Feedback Systems Specifically, is there a secure Patient feedback system, available, accessible? | B32: 4 | C32: 3 | D32: 1 | G32: =IF(SUM(B32:F32)>0,ROUND((B32+C32*2+D32*3+E32*4+F32*5)/(SUM(B32:F32)),0),0) -> 2 | H32: =SUM(B32:F32) -> 8
A33: ='GDHM Questions'!AE1 -> Indicator 23 -Population health management contribution of digital health Are current country digital health initiatives contributing to public health reporting and decision making? | C33: 4 | D33: 2 | E33: 2 | G33: =IF(SUM(B33:F33)>0,ROUND((B33+C33*2+D33*3+E33*4+F33*5)/(SUM(B33:F33)),0),0) -> 3 | H33: =SUM(B33:F33) -> 8

Sheet GDHM Scores
A2: Leadership & Governance | B2: =ROUND(IF(AVERAGE('Raw Data'!G3:G8)<1,1,AVERAGE('Raw Data'!G3:G8)),0) -> 3
A3: Strategy & Investment | B3: =ROUND(IF(AVERAGE('Raw Data'!G9:G12)<1,1,AVERAGE('Raw Data'!G9:G12)),0) -> 3
A4: Legislation, Policy, & Compliance | B4: =ROUND(IF(AVERAGE('Raw Data'!G13:G17)<1,1,AVERAGE('Raw Data'!G13:G17)),0) -> 2
A5: Workforce | B5: =ROUND(IF(AVERAGE('Raw Data'!G18:G21)<1,1,AVERAGE('Raw Data'!G18:G21)),0) -> 2
A6: Standards & Interoperability | B6: =ROUND(IF(AVERAGE('Raw Data'!G22:G23)<1,1,AVERAGE('Raw Data'!G22:G23)),0) -> 2
A7: Infrastructure | B7: =ROUND((IF('Raw Data'!G24=0,1,0) + IF('Raw Data'!G24>75,5,0) + IF(AND(0<'Raw Data'!G24,'Raw Data'!G24<26),2,0) + IF(AND(25<'Raw Data'!G24,'Raw Data'!G24<51),3,0) + IF(AND(50<'Raw Data'!G24,'Raw Data'!G24<76),4,0) + 'Raw Data'!G25)/2,0) -> 3
A8: Services & Applications | B8: =ROUND(IF(AVERAGE('Raw Data'!G26:G33)<1,1,AVERAGE('Raw Data'!G26:G33)),0) -> 3
B9: =AVERAGE(B2:B8) -> 2.5714286 | C9: Overall Score

Sheet Spider Graph
